README.rst
setup.py
drf_logged_validation_error/__init__.py
drf_logged_validation_error.egg-info/PKG-INFO
drf_logged_validation_error.egg-info/SOURCES.txt
drf_logged_validation_error.egg-info/dependency_links.txt
drf_logged_validation_error.egg-info/not-zip-safe
drf_logged_validation_error.egg-info/requires.txt
drf_logged_validation_error.egg-info/top_level.txt