Metadata-Version: 1.0
Name: drf-logged-validation-error
Version: 0.1
Summary: Raise validation with log in Django REST Framework API
Home-page: https://gitlab.com/taelimoh/drf_logged_validation_error
Author: Tae-lim Oh
Author-email: taelimoh@gmail.com
License: MIT
Keywords: django rest framework log validation error
Platform: UNKNOWN
